codeblock.py
setup.py
codeblock.egg-info/PKG-INFO
codeblock.egg-info/SOURCES.txt
codeblock.egg-info/dependency_links.txt
codeblock.egg-info/entry_points.txt
codeblock.egg-info/not-zip-safe
codeblock.egg-info/requires.txt
codeblock.egg-info/top_level.txt
