Metadata-Version: 1.0
Name: codeblock
Version: 0.1
Summary: Syntax-highlighted code blocks for docutils
Home-page: http://aspn.activestate.com/ASPN/Cookbook/Python/Recipe/252170
Author: Kevin Schluff (packaged by Jim Fulton)
Author-email: UNKNOWN
License: Python Cookbook code is freely available for use and review.
Platform: UNKNOWN
